jsonltojson/__init__.py
jsonltojson/formatters.py
jsonltojson-1.0.0.dist-info/LICENSE.txt
jsonltojson-1.0.0.dist-info/METADATA
jsonltojson-1.0.0.dist-info/WHEEL
jsonltojson-1.0.0.dist-info/top_level.txt
jsonltojson-1.0.0.dist-info/RECORD
