Metadata-Version: 2.1
Name: jsonltojson
Version: 1.0.0
Summary: A Python package for formatting JSONL files to a single JSON array
Author-email: Ismail Ibrahim <ismailsoftdev@gmail.com>
Project-URL: Homepage, https://github.com/ismailsoftdev/jsonltojson
Project-URL: Bug Tracker, https://github.com/ismailsoftdev/jsonltojson/issues
Classifier: Programming Language :: Python :: 3
Classifier: License :: OSI Approved :: MIT License
Classifier: Operating System :: OS Independent
Requires-Python: >=3.7
License-File: LICENSE.txt
